pickledbod.py
pickleDBod-0.9.5.dist-info/LICENSE
pickleDBod-0.9.5.dist-info/METADATA
pickleDBod-0.9.5.dist-info/WHEEL
pickleDBod-0.9.5.dist-info/top_level.txt
pickleDBod-0.9.5.dist-info/RECORD
