Metadata-Version: 2.1
Name: pickleDBod
Version: 0.9.5
Summary: A lightweight and simple database using json.
Home-page: http://github.com/patx/pickledb
Author: Harrison Erd
Author-email: erdh@mail.broward.edu
License: three-clause BSD
Platform: UNKNOWN
Classifier: Programming Language :: Python
Classifier: License :: OSI Approved :: BSD License
Classifier: Intended Audience :: Developers
Classifier: Topic :: Database
